psi_fusion_insights/__init__.py
psi_fusion_insights/main.py
psi_fusion_insights/prompts.py
psi_fusion_insights-2025.12.22075804.dist-info/METADATA
psi_fusion_insights-2025.12.22075804.dist-info/WHEEL
psi_fusion_insights-2025.12.22075804.dist-info/top_level.txt
psi_fusion_insights-2025.12.22075804.dist-info/RECORD
