Metadata-Version: 2.4
Name: psi-fusion-insights
Version: 2025.12.22075804
Summary: psi-fusion-insights extracts structured data from PsiQuantum fusion tech texts, summarizing techniques, benefits, challenges, and uses.
Author-email: psi-fusion-insights <hi@eugene.plus>
License: MIT
Project-URL: Homepage, https://github.com/chigwell/psi-fusion-insights
Requires-Python: >=3.9
Requires-Dist: langchain-llm7>=0.0.0
Requires-Dist: llmatch-messages>=0.0.0
Requires-Dist: langchain-core>=0.3.0
